{
  "products": [
    {
      "id": 1,
      "title": "Macbook Air",
      "price": "920",
      "year": 2023,
      "image": "assets/images/macbook.png",
      "configuration": {
        "chip": "M15",
        "ssd": "255 GB",
        "memory": "16 GB",
        "display": "Retina"
      }
    },
    {
      "id": 2,
      "title": "Macbook Pro",
      "price": 1000,
      "year": 2022,
      "image": "assets/images/macbook.png",
      "configuration": {
        "chip": "M1",
        "ssd": "500 GB",
        "memory": "16 GB",
        "display": "Hello"
      }
    },
    {
      "id": 3,
      "title": "Macbook Pro (Intel)",
      "price": 1300,
      "year": 2020,
      "image": "assets/images/macbook.png",
      "configuration": {
        "chip": "M1",
        "ssd": "1000 GB",
        "memory": "32 GB",
        "display": "Retina"
      }
    },
    {
      "id": 4,
      "title": "Iphone",
      "price": "3000",
      "year": "2026",
      "image": "assets/images/macbook.png",
      "configuration": {
        "chip": "M5",
        "ssd": "2TB",
        "memory": "33",
        "display": "FULL HD 2"
      }
    }
  ]
}